turtlecolors/__init__.py
turtlecolors/__main__.py
turtlecolors-0.0.8.dist-info/METADATA
turtlecolors-0.0.8.dist-info/WHEEL
turtlecolors-0.0.8.dist-info/licenses/LICENSE.txt
turtlecolors-0.0.8.dist-info/RECORD
