Metadata-Version: 2.4
Name: turtlecolors
Version: 0.0.8
Summary: A pure Python tkinter app for demonstrating RGB color values.
Project-URL: Homepage, https://github.com/asweigart/turtlecolors
Project-URL: Issues, https://github.com/asweigart/turtlecolors/issues
Author-email: Al Sweigart <al@inventwithpython.com>
License-File: LICENSE.txt
Classifier: Operating System :: OS Independent
Classifier: Programming Language :: Python :: 3
Requires-Python: >=2.7
